Metadata-Version: 2.1
Name: odoo14-addon-stock_picking_analytic
Version: 14.0.1.0.1.dev10
Summary: Allows to define the analytic account on picking level
Home-page: https://github.com/OCA/account-analytic
Author: ACSONE SA/NV,Odoo Community Association (OCA)
Author-email: support@odoo-community.org
License: AGPL-3
Classifier: Programming Language :: Python
Classifier: Framework :: Odoo
Classifier: Framework :: Odoo :: 14.0
Classifier: License :: OSI Approved :: GNU Affero General Public License v3
Requires-Python: >=3.6
Requires-Dist: odoo14-addon-base-view-inheritance-extension
Requires-Dist: odoo14-addon-stock-analytic
Requires-Dist: odoo<14.1dev,>=14.0a
